{
  "process_id": "E002",
  "family": "edm_neutrino",
  "family_original": "edm_neutrino",
  "tier": "PRIMARY",
  "standard_notation": "d_mu",
  "process_name": "Muon electric dipole moment",
  "owner": "PKA",
  "fact_check_verdict": "VERIFIED",
  "implementation_difficulty": "HIGH",
  "implementation_difficulty_reason": "Requires a new flavor-diagonal CP-odd lepton dipole observable, lepton/KK loop matching, and likely SMEFT-to-low-energy running. Existing Delta F=2 utilities and the mu->e gamma NDA helper do not compute d_mu.",
  "cycle_count": null,
  "priority_rationale": null,
  "promoted_in_wave": null,
  "code_coverage": {
    "status": "NO",
    "searched_paths": [
      "quarkConstraints",
      "qcd",
      "flavorConstraints",
      "neutrinos",
      "yukawa",
      "warpConfig",
      "solvers",
      "scanParams",
      "tests"
    ],
    "commands": [
      "rg -n 'muEDM|muon.?EDM|muon electric dipole' quarkConstraints qcd flavorConstraints neutrinos yukawa warpConfig solvers scanParams tests -g '!*.ipynb'",
      "rg -n '(^|[^[:alnum:]_])d_mu([^[:alnum:]_]|$)|(^|[^[:alnum:]_])dmu([^[:alnum:]_]|$)' quarkConstraints qcd flavorConstraints neutrinos yukawa warpConfig solvers scanParams tests -g '!*.ipynb'",
      "rg -n 'electric dipole|EDM' quarkConstraints qcd flavorConstraints neutrinos yukawa warpConfig solvers scanParams tests -g '!*.ipynb'",
      "rg -n 'muToEGamma|check_mu_to_e_gamma|PREFAC_BR|BR_LIMIT' flavorConstraints scanParams tests -g '!*.ipynb'",
      "rg -n \"epsilon_K|epsilon_k|Delta m_K|DELTA_M_K|evaluate_delta_mk|B_d|b_d|B_s|b_s|D0|d_mix|mu.?e.?gamma|muToEGamma|BR_LIMIT|MEG\" quarkConstraints flavorConstraints scanParams neutrinos yukawa qcd scripts tests docs -g '!*.ipynb'",
      "rg -n \"b.?->.?s|X_s|K\\\\*|R_K|R_D|B_s.*mu|pi.*nu|nu.*nubar|epsilon.?prime|eps.?prime|t.?->|Z.?->|h.?->|EDM|dipole|conversion|tau.?->|mu.?->.?3e\" quarkConstraints flavorConstraints scanParams neutrinos yukawa qcd scripts tests docs -g '!*.ipynb'",
      "rg -n \"MODERN_PHENOMENOLOGY_SYSTEM_IDS|DEFAULT_DELTA_F2_INPUTS|evaluate_bd_mixing|evaluate_bs_mixing|evaluate_d0_mixing|check_mu_to_e_gamma\" quarkConstraints flavorConstraints scanParams tests docs -g '!*.ipynb'"
    ],
    "findings": [
      "Focused greps for muEDM, muon EDM, muon electric dipole, d_mu, and dmu over the required implementation/test directories returned no relevant muon-EDM implementation.",
      "A broader d_mu-like grep produced only false positives for hadronic scales such as m_d_mu_had_GeV, not the muon EDM observable.",
      "A focused electric dipole/EDM grep over the required implementation/test directories returned no matches.",
      "flavorConstraints/muToEGamma.py:3, flavorConstraints/muToEGamma.py:21, and flavorConstraints/muToEGamma.py:81 implement an off-diagonal mu->e gamma dipole constraint, not the flavor-diagonal muon EDM.",
      "scanParams/scan.py:33 records a MEG II mu->e gamma branching-fraction bound, not a muon EDM constraint."
    ]
  },
  "code_coverage_status": "NO",
  "pdg_values": [
    {
      "label": "Adelmann2021:E002:muon_momentum",
      "observable": "PSI frozen-spin muEDM proposal muon momentum",
      "value": 125,
      "uncertainty": null,
      "units": "MeV/c",
      "display": null,
      "year": 2021,
      "experiment": null,
      "source_url": "https://arxiv.org/abs/2102.08838",
      "snapshot_path": "flavor_catalog/references/E002/adelmann2021_arxiv2102_08838.txt",
      "sha256": "bc86e027b5ee19d67663739ef540fe8f3420045c57cbbbf416caa465fec529c5",
      "access_date": "2026-05-16",
      "cl": null,
      "limit_type": null
    },
    {
      "label": "Adelmann2021:E002:magnetic_field",
      "observable": "PSI frozen-spin muEDM proposal magnetic field magnitude",
      "value": 3,
      "uncertainty": null,
      "units": "T",
      "display": null,
      "year": 2021,
      "experiment": null,
      "source_url": "https://arxiv.org/abs/2102.08838",
      "snapshot_path": "flavor_catalog/references/E002/adelmann2021_arxiv2102_08838.txt",
      "sha256": "bc86e027b5ee19d67663739ef540fe8f3420045c57cbbbf416caa465fec529c5",
      "access_date": "2026-05-16",
      "cl": null,
      "limit_type": null
    },
    {
      "label": "Adelmann2021:E002:rest_frame_electric_field",
      "observable": "PSI frozen-spin muEDM proposal rest-frame electric field",
      "value": 1,
      "uncertainty": null,
      "units": "GV/m",
      "display": null,
      "year": 2021,
      "experiment": null,
      "source_url": "https://arxiv.org/abs/2102.08838",
      "snapshot_path": "flavor_catalog/references/E002/adelmann2021_arxiv2102_08838.txt",
      "sha256": "bc86e027b5ee19d67663739ef540fe8f3420045c57cbbbf416caa465fec529c5",
      "access_date": "2026-05-16",
      "cl": null,
      "limit_type": null
    },
    {
      "label": "Adelmann2021:E002:sensitivity",
      "observable": "PSI frozen-spin muEDM proposal expected EDM sensitivity",
      "value": 6e-23,
      "uncertainty": null,
      "units": "e cm",
      "display": null,
      "year": 2021,
      "experiment": null,
      "source_url": "https://arxiv.org/abs/2102.08838",
      "snapshot_path": "flavor_catalog/references/E002/adelmann2021_arxiv2102_08838.txt",
      "sha256": "bc86e027b5ee19d67663739ef540fe8f3420045c57cbbbf416caa465fec529c5",
      "access_date": "2026-05-16",
      "cl": null,
      "limit_type": null
    },
    {
      "label": "Renga2024:E002:first_phase_target_year",
      "observable": "PSI muEDM status first-phase feasibility target",
      "value": 2026,
      "uncertainty": null,
      "units": "calendar year",
      "display": null,
      "year": 2024,
      "experiment": null,
      "source_url": "https://arxiv.org/abs/2409.20050",
      "snapshot_path": "flavor_catalog/references/E002/renga2024_arxiv2409_20050.txt",
      "sha256": "c9c8a8cb2c324a8e46aa106aeacbe3cdb01e4c33cefb7ce8ebcdf339844d4728",
      "access_date": "2026-05-16",
      "cl": null,
      "limit_type": null
    },
    {
      "label": "Renga2024:E002:ultimate_improvement_factor",
      "observable": "PSI muEDM status ultimate sensitivity-improvement goal",
      "value": 100,
      "uncertainty": null,
      "units": "improvement factor",
      "display": null,
      "year": 2024,
      "experiment": null,
      "source_url": "https://arxiv.org/abs/2409.20050",
      "snapshot_path": "flavor_catalog/references/E002/renga2024_arxiv2409_20050.txt",
      "sha256": "c9c8a8cb2c324a8e46aa106aeacbe3cdb01e4c33cefb7ce8ebcdf339844d4728",
      "access_date": "2026-05-16",
      "cl": null,
      "limit_type": null
    },
    {
      "label": "Renga2024:E002:ultimate_goal_period",
      "observable": "PSI muEDM status ultimate-goal period",
      "value": "early 2030s",
      "uncertainty": null,
      "units": "time period",
      "display": null,
      "year": 2024,
      "experiment": null,
      "source_url": "https://arxiv.org/abs/2409.20050",
      "snapshot_path": "flavor_catalog/references/E002/renga2024_arxiv2409_20050.txt",
      "sha256": "c9c8a8cb2c324a8e46aa106aeacbe3cdb01e4c33cefb7ce8ebcdf339844d4728",
      "access_date": "2026-05-16",
      "cl": null,
      "limit_type": null
    }
  ],
  "supporting_measurements": null,
  "paper_era_reference": null,
  "theory_context": null,
  "auxiliary_theory_inputs": null,
  "post_2010_developments": null,
  "source_shas": {
    "pdg2026_muon_edm_datablock.txt": "sha256:2918e0eb78197361ba039efd061cde1c119e70626d691b5bdaa50b625b2e08c1",
    "bennett2009_arxiv0811_1207.txt": "sha256:16ce7a84e7baff9e76d9a96ded01ddfc590057ab8f22f51b9dfd8afc5b878362",
    "adelmann2021_arxiv2102_08838.txt": "sha256:bc86e027b5ee19d67663739ef540fe8f3420045c57cbbbf416caa465fec529c5",
    "renga2024_arxiv2409_20050.txt": "sha256:c9c8a8cb2c324a8e46aa106aeacbe3cdb01e4c33cefb7ce8ebcdf339844d4728",
    "cfw2008_arxiv0804_1954.txt": "sha256:b4addc6c76bc52bb5b99d1253061b3fa1a5b8e6353d9ded999bbc62813832c3b"
  },
  "source_shas_count": 5,
  "access_dates": [
    "2026-05-16"
  ],
  "latest_status": "FACT-CHECKED",
  "status_history": [
    {
      "state": "WRITER-INITIATED",
      "timestamp": "2026-05-16T14:07:18-04:00",
      "from": null,
      "to": "WRITER-INITIATED",
      "at": "2026-05-16T14:07:18-04:00",
      "agent_id": "PKA-E002",
      "reason": "Initial PKA source extraction and draft started."
    },
    {
      "state": "PKA-DONE",
      "timestamp": "2026-05-16T14:07:18-04:00",
      "from": "WRITER-INITIATED",
      "to": "PKA-DONE",
      "at": "2026-05-16T14:07:18-04:00",
      "agent_id": "PKA-E002",
      "reason": "PKA draft, minimal source snapshots, and code-coverage grep completed."
    },
    {
      "state": "WRITER-DONE",
      "timestamp": "2026-05-16T14:23:54-04:00",
      "from": "PKA-DONE",
      "to": "WRITER-DONE",
      "at": "2026-05-16T14:23:54-04:00",
      "agent": "WA",
      "agent_id": "WA",
      "reason": "Writer polish completed for batch wa_w5a_charged_lepton_edm."
    },
    {
      "state": "WRITER-REWORK",
      "timestamp": "2026-05-16T14:44:30-04:00",
      "from": "WRITER-DONE",
      "to": "WRITER-REWORK",
      "at": "2026-05-16T14:44:30-04:00",
      "agent": "CA",
      "agent_id": "CA",
      "reason": "Checker ca_w5a_charged_lepton_edm found a strict CHK-1 metadata-placement issue.",
      "issues": [
        "CHK-1: E002.tex quotes PSI projection/status numbers (125 MeV/c, 3 T, 1 GV/m, <=6e-23 e cm, 2026, factor 100, early 2030s), but those values are in auxiliary_values rather than pdg_or_equivalent entries with the required per-claim metadata."
      ]
    },
    {
      "state": "WRITER-DONE",
      "timestamp": "2026-05-16T15:15:17-04:00",
      "from": "WRITER-REWORK",
      "to": "WRITER-DONE",
      "at": "2026-05-16T15:15:17-04:00",
      "agent": "WA-v2",
      "agent_id": "WA-v2",
      "cycle": 2,
      "reason": "WA cycle 2 addressed CA CHK-1 by adding pdg_or_equivalent.values metadata for the flagged PSI projection/status numbers."
    },
    {
      "state": "CHECKER-DONE",
      "timestamp": "2026-05-16T15:30:46-04:00",
      "from": "WRITER-DONE",
      "to": "CHECKER-DONE",
      "at": "2026-05-16T15:30:46-04:00",
      "agent": "CA",
      "agent_id": "CA",
      "cycle": 2,
      "reason": "Checker cycle 2 ca_w5a_charged_lepton_edm_v2 verified WA-v2 traceability and checklist items CHK-1..CHK-8."
    },
    {
      "from": "CHECKER-DONE",
      "to": "OPUS-APPROVED",
      "state": "OPUS-APPROVED",
      "at": "2026-05-16T17:30:00-04:00",
      "timestamp": "2026-05-16T17:30:00-04:00",
      "agent": "Opus-round-2",
      "agent_id": "Opus-round-2",
      "round_id": "opus_round_002",
      "reason": "Opus round 2 per-process sign-off; CA-verified PASS retained; see flavor_catalog/signoff/round_002_index.md."
    },
    {
      "state": "FACT-CHECKED",
      "timestamp": "2026-05-16T17:45:00-04:00",
      "from": "OPUS-APPROVED",
      "to": "FACT-CHECKED",
      "at": "2026-05-16T17:45:00-04:00",
      "agent": "factcheck-codex-edm_neutrino",
      "agent_id": "factcheck-codex-edm_neutrino",
      "verdict": "VERIFIED",
      "findings_count": 0,
      "notes": "Muon EDM PDG/Bennett values and PSI projection/status numbers verified against fetched PDG and arXiv sources."
    }
  ],
  "sections": {
    "process": "\\textbf{Standard notation:} \\(d_\\mu\\).  This entry covers the flavor-diagonal\nCP-odd electric dipole moment of the muon, cataloged in the\n\\texttt{edm\\_neutrino} family.  It is an EDM-adjacent lepton-sector process,\nnot a charged-lepton-flavor-violating decay and not a quark \\(\\Delta F=2\\)\nobservable.",
    "pdg_prose": "The sidecar block \\texttt{pdg\\_or\\_equivalent.canonical\\_direct\\_limit}, from\nPDG Live 2026 (\\texttt{PDG2026:MuonEDM}), lists the canonical direct\nexperimental bound as\n\\[\n  |d_\\mu| < 1.8\\times10^{-19}\\ e\\,\\mathrm{cm}\n  \\qquad (95\\%~\\mathrm{CL}),\n\\]\nfrom the Bennett et al. BNL E821 storage-ring analysis; see\n\\texttt{flavor\\_catalog/references/E002/pdg2026\\_muon\\_edm\\_datablock.txt}.\nThe sidecar block \\texttt{pdg\\_or\\_equivalent.pdg\\_combined\\_measurement}\nrecords the combined result as\n\\((0.0\\pm0.9)\\times10^{-19}\\ e\\,\\mathrm{cm}\\).  The\n\\texttt{pdg\\_or\\_equivalent.primary\\_bnl\\_measurement} block, from\n\\texttt{Bennett:MuonEDM2009}, reports\n\\(d_\\mu=-0.1(0.9)\\times10^{-19}\\ e\\,\\mathrm{cm}\\) and quotes\n\\(|d_\\mu|<1.9\\times10^{-19}\\ e\\,\\mathrm{cm}\\) at \\(95\\%\\) CL.",
    "relevance": "A nonzero \\(d_\\mu\\) probes the imaginary part of the flavor-diagonal muon\ndipole operator, schematically\n\\(\\bar\\mu\\sigma_{\\alpha\\beta}\\gamma_5\\mu F^{\\alpha\\beta}\\).  In warped\nlepton extensions, anarchic charged-lepton and neutrino Yukawa structures can\ngenerate such dipoles through loop matching involving KK leptons, Higgs\ndynamics, or gauge-sector phases.  The process therefore diagnoses CP\nalignment in the muon sector, complementary to \\(\\mu\\to e\\gamma\\), but it does\nnot directly constrain the existing quark-only scan.",
    "post_2008": "Relative to the 2008 CFW warped-flavor reference point\n(\\texttt{CsakiFalkowskiWeiler:RSFlavor2008}), the key direct experimental\ndevelopment is the BNL E821 publication in 2009.  That analysis used muon\n\\(g-2\\) storage-ring spin-precession data and remains the basis of the PDG\ndirect limit.  The major post-2008 prospective change is the dedicated PSI\nmuEDM program.  The 2021 PSI letter of intent\n\\texttt{auxiliary\\_values.psi\\_frozen\\_spin\\_projection}\n(\\texttt{Adelmann:MuonEDMPSI2021}) proposes a frozen-spin search with\n\\(p=125~\\mathrm{MeV}/c\\), \\(|B|=3~\\mathrm{T}\\), a rest-frame electric field\nof \\(1~\\mathrm{GV/m}\\), and an expected sensitivity\n\\(\\sigma(d_\\mu)\\leq6\\times10^{-23}\\ e\\,\\mathrm{cm}\\).  The\n\\texttt{auxiliary\\_values.psi\\_2024\\_status} entry\n(\\texttt{Renga:MuonEDMStatus2024}) describes a first phase aimed at\ndemonstrating feasibility by 2026, with an ultimate goal of improving the\nsensitivity by a factor of \\(100\\) by the early 2030s.",
    "validity": "The PDG number is a robust direct storage-ring bound on a static muon EDM.\nIts interpretation in RS is model-dependent: a live constraint requires the\nlepton-sector CP phases, the dipole matching scale, and the treatment of\nSMEFT/low-energy running to be fixed.  The PSI entries are projections and\nshould be treated as roadmap information, not current exclusions.",
    "code_coverage_prose": "\\textbf{NO.}  Focused greps for \\texttt{muEDM}, \\texttt{muon.?EDM},\n\\texttt{muon electric dipole}, \\texttt{d\\_mu}, and \\texttt{dmu} over\n\\texttt{quarkConstraints/}, \\texttt{qcd/}, \\texttt{flavorConstraints/},\n\\texttt{neutrinos/}, \\texttt{yukawa/}, \\texttt{warpConfig/},\n\\texttt{solvers/}, \\texttt{scanParams/}, and \\texttt{tests/} found no muon-EDM\nimplementation.  The nearby dipole code is the off-diagonal\n\\(\\mu\\to e\\gamma\\) helper in \\texttt{flavorConstraints/muToEGamma.py:3},\n\\texttt{:21}, and \\texttt{:81}, with the MEG II branching-fraction default at\n\\texttt{scanParams/scan.py:33}; that is a different observable.",
    "implementation_difficulty_prose": "\\textbf{HIGH.}  A production implementation needs a new flavor-diagonal\nCP-odd lepton dipole observable, loop matching from the lepton/KK sector, and\nlikely SMEFT-to-low-energy running.  The existing \\(\\Delta F=2\\) basis and the\n\\(\\mu\\to e\\gamma\\) NDA helper do not calculate \\(d_\\mu\\).",
    "key_references": "Process-local source keys before bibliography consolidation:\n\\texttt{PDG2026:MuonEDM}, \\texttt{Bennett:MuonEDM2009},\n\\texttt{Adelmann:MuonEDMPSI2021}, \\texttt{Renga:MuonEDMStatus2024}, and\n\\texttt{CsakiFalkowskiWeiler:RSFlavor2008}."
  },
  "source_yaml": "flavor_catalog/processes/edm_neutrino/E002.yaml",
  "source_tex": "flavor_catalog/processes/edm_neutrino/E002.tex",
  "worklog_path": "flavor_catalog/worklogs/E002/"
}